bprune/__init__.py
bprune/src/Prune_BNN.py
bprune/src/Viz_Plotting.py
bprune/src/__init__.py
bprune/src/utils.py
example/Prune_BNN_CIFAR10_Model.py
example/Prune_BNN_MNIST_Model.py
example/__init__.py
test/__init__.py
test/demo_run.py
test/test_bprune.py
BPrune-0.0.1.dist-info/LICENSE
BPrune-0.0.1.dist-info/METADATA
BPrune-0.0.1.dist-info/WHEEL
BPrune-0.0.1.dist-info/top_level.txt
BPrune-0.0.1.dist-info/RECORD
