Metadata-Version: 2.1
Name: BPrune
Version: 0.0.1
Summary: Bayesiean Neural Network Pruning Library
Home-page: https://github.com/Himscipy/BPrune/
Author: Himanshu Sharma
Author-email: himanshu90sharma@gmail.com
License: MIT
Keywords: Neural Network,TensorFlow Probability,Bayesian Neural Network,Deep Learning
Platform: UNKNOWN
Classifier: Development Status :: 3 - Alpha
Classifier: Intended Audience :: Developers
Classifier: Topic :: Software Development :: Build Tools
Classifier: License :: OSI Approved :: MIT License
Classifier: Programming Language :: Python :: 3
Classifier: Programming Language :: Python :: 3.4
Classifier: Programming Language :: Python :: 3.5
Classifier: Programming Language :: Python :: 3.6
Classifier: Programming Language :: Python :: 3.7
Requires-Dist: markdown
Requires-Dist: numpy
Requires-Dist: scipy
Requires-Dist: pandas
Requires-Dist: seaborn
Requires-Dist: tensorflow
Requires-Dist: tensorflow-probability
